pyxbst/__init__.py
pyxbst-0.0.2.dist-info/LICENSE
pyxbst-0.0.2.dist-info/METADATA
pyxbst-0.0.2.dist-info/WHEEL
pyxbst-0.0.2.dist-info/top_level.txt
pyxbst-0.0.2.dist-info/RECORD
