Metadata-Version: 2.1
Name: pyxbst
Version: 0.0.2
Summary: A Python library for extended branching search trees.
Home-page: https://github.com/benmhamed-a/pyxbst
Author: Abdelouahed Ben Mhamed
Author-email: a.benmhamed@intelligentica.net
License: UNKNOWN
Platform: UNKNOWN
Classifier: Programming Language :: Python :: 3
Classifier: License :: OSI Approved :: MIT License
Classifier: Operating System :: OS Independent
Requires-Python: >=3.6
